{
  "recommendations": [
    {
      "rank": 1,
      "title": "Data Scientist",
      "experience_level": "Mid-Level",
      "match_score": 0.78,
      "matched_skills": ["Python", "SQL"],
      "missing_skills": ["Machine Learning", "TensorFlow", "Pandas", "Data Visualization"]
    },
    {
      "rank": 2,
      "title": "Machine Learning Engineer",
      "experience_level": "Junior",
      "match_score": 0.65,
      "matched_skills": ["Python", "SQL"],
      "missing_skills": ["TensorFlow", "PyTorch", "Scikit-learn", "Docker"]
    },
    {
      "rank": 3,
      "title": "Data Analyst",
      "experience_level": "Entry-Level",
      "match_score": 0.61,
      "matched_skills": ["Python", "SQL"],
      "missing_skills": ["Excel", "Tableau", "Statistics"]
    }
  ]
}
